{
  "gviem_create_time": "1764574373646",
  "gviem": "LbLF2KoBRvf9tToHXzjls0ace",
  "nid18_create_time": "1764574373646",
  "st_asi": "delete",
  "st_sn": "1",
  "st_sp": "2025-12-01%2015%3A32%3A53",
  "nid18": "0f6bb4d8ce08d8a0d98c166dbe5387fb",
  "st_inirUrl": "",
  "st_psi": "20251201153253495-113200301321-2134018037",
  "st_pvi": "02340448010458",
  "st_si": "15378117094386",
  "fullscreengg": "1",
  "fullscreengg2": "1",
  "st_nvi": "Lc8M2-mFPSPNOlb2osuydcaf0",
  "qgqp_b_id": "d652afdb863504c343a2eedd2c7c0a06"
}